tatsu/__init__.py
tatsu/data_structures.py
tatsu/error.py
tatsu/wrapper.py
tatsu.py-1.1.0.dist-info/LICENSE.txt
tatsu.py-1.1.0.dist-info/METADATA
tatsu.py-1.1.0.dist-info/WHEEL
tatsu.py-1.1.0.dist-info/top_level.txt
tatsu.py-1.1.0.dist-info/RECORD
