Metadata-Version: 2.1
Name: tatsu.py
Version: 1.1.0
Summary: An async python API Wrapper for the Tatsu API.
Home-page: https://github.com/PumPum7/Tatsu.py
Author: Pum
License: MIT License
Project-URL: Tatsu, https://tatsu.gg/
Project-URL: Source, https://github.com/PumPum7/Tatsu.py
Keywords: api,tatsu,api wrapper
Classifier: Programming Language :: Python :: 3
Classifier: License :: OSI Approved :: MIT License
Classifier: Operating System :: OS Independent
License-File: LICENSE.txt
Requires-Dist: ratelimit ~=2.2.1
Requires-Dist: httpx ~=0.27.0
